mne_lsl/__init__.py
mne_lsl/__init__.pyi
mne_lsl/_typing.py
mne_lsl/_typing.pyi
mne_lsl/_version.py
mne_lsl/_commands/__init__.py
mne_lsl/_commands/__init__.pyi
mne_lsl/_commands/main.py
mne_lsl/_commands/main.pyi
mne_lsl/_commands/player.py
mne_lsl/_commands/player.pyi
mne_lsl/_commands/sys_info.py
mne_lsl/_commands/sys_info.pyi
mne_lsl/_commands/viewer.py
mne_lsl/_commands/viewer.pyi
mne_lsl/datasets/__init__.py
mne_lsl/datasets/__init__.pyi
mne_lsl/datasets/_fetch.py
mne_lsl/datasets/_fetch.pyi
mne_lsl/datasets/sample-registry.txt
mne_lsl/datasets/sample.py
mne_lsl/datasets/sample.pyi
mne_lsl/datasets/testing-registry.txt
mne_lsl/datasets/testing.py
mne_lsl/datasets/testing.pyi
mne_lsl/lsl/__init__.py
mne_lsl/lsl/__init__.pyi
mne_lsl/lsl/_utils.py
mne_lsl/lsl/_utils.pyi
mne_lsl/lsl/constants.py
mne_lsl/lsl/functions.py
mne_lsl/lsl/functions.pyi
mne_lsl/lsl/load_liblsl.py
mne_lsl/lsl/load_liblsl.pyi
mne_lsl/lsl/stream_info.py
mne_lsl/lsl/stream_info.pyi
mne_lsl/lsl/stream_inlet.py
mne_lsl/lsl/stream_inlet.pyi
mne_lsl/lsl/stream_outlet.py
mne_lsl/lsl/stream_outlet.pyi
mne_lsl/lsl/lib/liblsl.so.1.16.2
mne_lsl/player/__init__.py
mne_lsl/player/__init__.pyi
mne_lsl/player/_base.py
mne_lsl/player/_base.pyi
mne_lsl/player/player_lsl.py
mne_lsl/player/player_lsl.pyi
mne_lsl/stream/__init__.py
mne_lsl/stream/__init__.pyi
mne_lsl/stream/_filters.py
mne_lsl/stream/_filters.pyi
mne_lsl/stream/_hpi.py
mne_lsl/stream/_hpi.pyi
mne_lsl/stream/base.py
mne_lsl/stream/base.pyi
mne_lsl/stream/epochs.py
mne_lsl/stream/epochs.pyi
mne_lsl/stream/stream_lsl.py
mne_lsl/stream/stream_lsl.pyi
mne_lsl/stream_viewer/__init__.py
mne_lsl/stream_viewer/stream_viewer.py
mne_lsl/stream_viewer/backends/__init__.py
mne_lsl/stream_viewer/backends/_backend.py
mne_lsl/stream_viewer/backends/pyqtgraph.py
mne_lsl/stream_viewer/control_gui/__init__.py
mne_lsl/stream_viewer/control_gui/_control.py
mne_lsl-1.11.0.dist-info/METADATA
mne_lsl-1.11.0.dist-info/WHEEL
mne_lsl-1.11.0.dist-info/entry_points.txt
mne_lsl-1.11.0.dist-info/top_level.txt
mne_lsl-1.11.0.dist-info/RECORD
mne_lsl-1.11.0.dist-info/licenses/LICENSE
