Metadata-Version: 2.4
Name: mne_lsl
Version: 1.11.0
Summary: Real-time framework integrated with MNE-Python for online neuroscience research through LSL-compatible devices.
Author-email: Mathieu Scheltienne <mathieu.scheltienne@gmail.com>
Maintainer-email: Mathieu Scheltienne <mathieu.scheltienne@gmail.com>
License: Copyright © 2023-2024, authors of MNE-LSL
Project-URL: documentation, https://mne.tools/mne-lsl
Project-URL: homepage, https://mne.tools/mne-lsl
Project-URL: source, https://github.com/mne-tools/mne-lsl
Project-URL: tracker, https://github.com/mne-tools/mne-lsl/issues
Keywords: brain,EEG,eeg,electroencephalography,labstreaminglayer,LSL,neuroimaging,neurophysiology,neuroscience,python,real-time
Classifier: Intended Audience :: Developers
Classifier: Intended Audience :: Science/Research
Classifier: Natural Language :: English
Classifier: Operating System :: MacOS
Classifier: Operating System :: Microsoft :: Windows
Classifier: Operating System :: Unix
Classifier: Programming Language :: Python :: 3 :: Only
Classifier: Programming Language :: Python :: 3.10
Classifier: Programming Language :: Python :: 3.11
Classifier: Programming Language :: Python :: 3.12
Classifier: Programming Language :: Python :: 3.13
Classifier: Programming Language :: Python :: 3.14
Classifier: Topic :: Scientific/Engineering
Classifier: Topic :: Software Development
Requires-Python: >=3.10
License-File: LICENSE
Requires-Dist: click>=8.1
Requires-Dist: mne>=1.6
Requires-Dist: numpy<3,>=1.21
Requires-Dist: packaging
Requires-Dist: pooch
Requires-Dist: psutil
Requires-Dist: pyqtgraph
Requires-Dist: qtpy
Requires-Dist: scipy
Requires-Dist: tomli; python_version < "3.11"
Dynamic: license-file
